[{"label":"S\u00e3o Paulo, Brazil","nb_visits":1337,"nb_actions":6346,"max_actions":73,"sum_visit_length":351966,"bounce_count":512,"nb_visits_converted":0,"sum_daily_nb_uniq_visitors":1154,"sum_daily_nb_users":0,"segment":"regionCode==SP;countryCode==br","region":"SP","country":"br","country_name":"Brazil","region_name":"S\u00e3o Paulo","logo":"plugins\/Morpheus\/icons\/dist\/flags\/br.png"},{"label":"Unknown","nb_visits":744,"nb_actions":3662,"max_actions":60,"sum_visit_length":247834,"bounce_count":309,"nb_visits_converted":0,"sum_daily_nb_uniq_visitors":623,"sum_daily_nb_users":0,"region":"xx","country":"xx","country_name":"Unknown","region_name":"Unknown","logo":"plugins\/Morpheus\/icons\/dist\/flags\/xx.png"},{"label":"Rio de Janeiro, Brazil","nb_visits":423,"nb_actions":2004,"max_actions":45,"sum_visit_length":121972,"bounce_count":172,"nb_visits_converted":0,"sum_daily_nb_uniq_visitors":366,"sum_daily_nb_users":0,"segment":"regionCode==RJ;countryCode==br","region":"RJ","country":"br","country_name":"Brazil","region_name":"Rio de Janeiro","logo":"plugins\/Morpheus\/icons\/dist\/flags\/br.png"},{"label":"Bahia, Brazil","nb_visits":215,"nb_actions":1365,"max_actions":70,"sum_visit_length":53464,"bounce_count":55,"nb_visits_converted":0,"sum_daily_nb_uniq_visitors":198,"sum_daily_nb_users":0,"segment":"regionCode==BA;countryCode==br","region":"BA","country":"br","country_name":"Brazil","region_name":"Bahia","logo":"plugins\/Morpheus\/icons\/dist\/flags\/br.png"},{"label":"Minas Gerais, Brazil","nb_visits":182,"nb_actions":956,"max_actions":42,"sum_visit_length":41833,"bounce_count":42,"nb_visits_converted":0,"sum_daily_nb_uniq_visitors":173,"sum_daily_nb_users":0,"segment":"regionCode==MG;countryCode==br","region":"MG","country":"br","country_name":"Brazil","region_name":"Minas Gerais","logo":"plugins\/Morpheus\/icons\/dist\/flags\/br.png"},{"label":"Rio Grande do Sul, Brazil","nb_visits":162,"nb_actions":736,"max_actions":66,"sum_visit_length":38032,"bounce_count":64,"nb_visits_converted":0,"sum_daily_nb_uniq_visitors":133,"sum_daily_nb_users":0,"segment":"regionCode==RS;countryCode==br","region":"RS","country":"br","country_name":"Brazil","region_name":"Rio Grande do Sul","logo":"plugins\/Morpheus\/icons\/dist\/flags\/br.png"},{"label":"Cear\u00e1, Brazil","nb_visits":153,"nb_actions":724,"max_actions":68,"sum_visit_length":29063,"bounce_count":53,"nb_visits_converted":0,"sum_daily_nb_uniq_visitors":143,"sum_daily_nb_users":0,"segment":"regionCode==CE;countryCode==br","region":"CE","country":"br","country_name":"Brazil","region_name":"Cear\u00e1","logo":"plugins\/Morpheus\/icons\/dist\/flags\/br.png"},{"label":"Paran\u00e1, Brazil","nb_visits":148,"nb_actions":761,"max_actions":100,"sum_visit_length":41113,"bounce_count":53,"nb_visits_converted":0,"sum_daily_nb_uniq_visitors":129,"sum_daily_nb_users":0,"segment":"regionCode==PR;countryCode==br","region":"PR","country":"br","country_name":"Brazil","region_name":"Paran\u00e1","logo":"plugins\/Morpheus\/icons\/dist\/flags\/br.png"},{"label":"Goi\u00e1s, Brazil","nb_visits":138,"nb_actions":744,"max_actions":56,"sum_visit_length":38579,"bounce_count":44,"nb_visits_converted":0,"sum_daily_nb_uniq_visitors":127,"sum_daily_nb_users":0,"segment":"regionCode==GO;countryCode==br","region":"GO","country":"br","country_name":"Brazil","region_name":"Goi\u00e1s","logo":"plugins\/Morpheus\/icons\/dist\/flags\/br.png"},{"label":"Pernambuco, Brazil","nb_visits":108,"nb_actions":375,"max_actions":26,"sum_visit_length":23992,"bounce_count":41,"nb_visits_converted":0,"sum_daily_nb_uniq_visitors":102,"sum_daily_nb_users":0,"segment":"regionCode==PE;countryCode==br","region":"PE","country":"br","country_name":"Brazil","region_name":"Pernambuco","logo":"plugins\/Morpheus\/icons\/dist\/flags\/br.png"},{"label":"Santa Catarina, Brazil","nb_visits":83,"nb_actions":391,"max_actions":48,"sum_visit_length":15367,"bounce_count":35,"nb_visits_converted":0,"sum_daily_nb_uniq_visitors":69,"sum_daily_nb_users":0,"segment":"regionCode==SC;countryCode==br","region":"SC","country":"br","country_name":"Brazil","region_name":"Santa Catarina","logo":"plugins\/Morpheus\/icons\/dist\/flags\/br.png"},{"label":"Esp\u00edrito Santo, Brazil","nb_visits":57,"nb_actions":200,"max_actions":14,"sum_visit_length":11860,"bounce_count":14,"nb_visits_converted":0,"sum_daily_nb_uniq_visitors":53,"sum_daily_nb_users":0,"segment":"regionCode==ES;countryCode==br","region":"ES","country":"br","country_name":"Brazil","region_name":"Esp\u00edrito Santo","logo":"plugins\/Morpheus\/icons\/dist\/flags\/br.png"},{"label":"Amazonas, Brazil","nb_visits":55,"nb_actions":252,"max_actions":26,"sum_visit_length":13640,"bounce_count":15,"nb_visits_converted":0,"sum_daily_nb_uniq_visitors":49,"sum_daily_nb_users":0,"segment":"regionCode==AM;countryCode==br","region":"AM","country":"br","country_name":"Brazil","region_name":"Amazonas","logo":"plugins\/Morpheus\/icons\/dist\/flags\/br.png"},{"label":"Para\u00edba, Brazil","nb_visits":52,"nb_actions":211,"max_actions":25,"sum_visit_length":8109,"bounce_count":20,"nb_visits_converted":0,"sum_daily_nb_uniq_visitors":46,"sum_daily_nb_users":0,"segment":"regionCode==PB;countryCode==br","region":"PB","country":"br","country_name":"Brazil","region_name":"Para\u00edba","logo":"plugins\/Morpheus\/icons\/dist\/flags\/br.png"},{"label":"Par\u00e1, Brazil","nb_visits":51,"nb_actions":271,"max_actions":31,"sum_visit_length":12418,"bounce_count":14,"nb_visits_converted":0,"sum_daily_nb_uniq_visitors":48,"sum_daily_nb_users":0,"segment":"regionCode==PA;countryCode==br","region":"PA","country":"br","country_name":"Brazil","region_name":"Par\u00e1","logo":"plugins\/Morpheus\/icons\/dist\/flags\/br.png"},{"label":"Maranh\u00e3o, Brazil","nb_visits":44,"nb_actions":212,"max_actions":22,"sum_visit_length":10175,"bounce_count":11,"nb_visits_converted":0,"sum_daily_nb_uniq_visitors":41,"sum_daily_nb_users":0,"segment":"regionCode==MA;countryCode==br","region":"MA","country":"br","country_name":"Brazil","region_name":"Maranh\u00e3o","logo":"plugins\/Morpheus\/icons\/dist\/flags\/br.png"},{"label":"Alagoas, Brazil","nb_visits":36,"nb_actions":172,"max_actions":32,"sum_visit_length":6564,"bounce_count":12,"nb_visits_converted":0,"sum_daily_nb_uniq_visitors":34,"sum_daily_nb_users":0,"segment":"regionCode==AL;countryCode==br","region":"AL","country":"br","country_name":"Brazil","region_name":"Alagoas","logo":"plugins\/Morpheus\/icons\/dist\/flags\/br.png"},{"label":"Mato Grosso, Brazil","nb_visits":33,"nb_actions":205,"max_actions":29,"sum_visit_length":5489,"bounce_count":9,"nb_visits_converted":0,"sum_daily_nb_uniq_visitors":31,"sum_daily_nb_users":0,"segment":"regionCode==MT;countryCode==br","region":"MT","country":"br","country_name":"Brazil","region_name":"Mato Grosso","logo":"plugins\/Morpheus\/icons\/dist\/flags\/br.png"},{"label":"Rio Grande do Norte, Brazil","nb_visits":30,"nb_actions":119,"max_actions":20,"sum_visit_length":8580,"bounce_count":9,"nb_visits_converted":0,"sum_daily_nb_uniq_visitors":30,"sum_daily_nb_users":0,"segment":"regionCode==RN;countryCode==br","region":"RN","country":"br","country_name":"Brazil","region_name":"Rio Grande do Norte","logo":"plugins\/Morpheus\/icons\/dist\/flags\/br.png"},{"label":"Tocantins, Brazil","nb_visits":30,"nb_actions":62,"max_actions":9,"sum_visit_length":1121,"bounce_count":17,"nb_visits_converted":0,"sum_daily_nb_uniq_visitors":28,"sum_daily_nb_users":0,"segment":"regionCode==TO;countryCode==br","region":"TO","country":"br","country_name":"Brazil","region_name":"Tocantins","logo":"plugins\/Morpheus\/icons\/dist\/flags\/br.png"},{"label":"Piau\u00ed, Brazil","nb_visits":26,"nb_actions":107,"max_actions":15,"sum_visit_length":4059,"bounce_count":10,"nb_visits_converted":0,"sum_daily_nb_uniq_visitors":26,"sum_daily_nb_users":0,"segment":"regionCode==PI;countryCode==br","region":"PI","country":"br","country_name":"Brazil","region_name":"Piau\u00ed","logo":"plugins\/Morpheus\/icons\/dist\/flags\/br.png"},{"label":"Mato Grosso do Sul, Brazil","nb_visits":19,"nb_actions":103,"max_actions":24,"sum_visit_length":3099,"bounce_count":2,"nb_visits_converted":0,"sum_daily_nb_uniq_visitors":18,"sum_daily_nb_users":0,"segment":"regionCode==MS;countryCode==br","region":"MS","country":"br","country_name":"Brazil","region_name":"Mato Grosso do Sul","logo":"plugins\/Morpheus\/icons\/dist\/flags\/br.png"},{"label":"Amap\u00e1, Brazil","nb_visits":18,"nb_actions":152,"max_actions":81,"sum_visit_length":5846,"bounce_count":9,"nb_visits_converted":0,"sum_daily_nb_uniq_visitors":15,"sum_daily_nb_users":0,"segment":"regionCode==AP;countryCode==br","region":"AP","country":"br","country_name":"Brazil","region_name":"Amap\u00e1","logo":"plugins\/Morpheus\/icons\/dist\/flags\/br.png"},{"label":"Rond\u00f4nia, Brazil","nb_visits":15,"nb_actions":48,"max_actions":7,"sum_visit_length":1333,"bounce_count":3,"nb_visits_converted":0,"sum_daily_nb_uniq_visitors":14,"sum_daily_nb_users":0,"segment":"regionCode==RO;countryCode==br","region":"RO","country":"br","country_name":"Brazil","region_name":"Rond\u00f4nia","logo":"plugins\/Morpheus\/icons\/dist\/flags\/br.png"},{"label":"Sergipe, Brazil","nb_visits":11,"nb_actions":56,"max_actions":15,"sum_visit_length":1888,"bounce_count":2,"nb_visits_converted":0,"sum_daily_nb_uniq_visitors":11,"sum_daily_nb_users":0,"segment":"regionCode==SE;countryCode==br","region":"SE","country":"br","country_name":"Brazil","region_name":"Sergipe","logo":"plugins\/Morpheus\/icons\/dist\/flags\/br.png"},{"label":"Acre, Brazil","nb_visits":10,"nb_actions":71,"max_actions":27,"sum_visit_length":3061,"bounce_count":6,"nb_visits_converted":0,"sum_daily_nb_uniq_visitors":10,"sum_daily_nb_users":0,"segment":"regionCode==AC;countryCode==br","region":"AC","country":"br","country_name":"Brazil","region_name":"Acre","logo":"plugins\/Morpheus\/icons\/dist\/flags\/br.png"},{"label":"England, United Kingdom","nb_visits":6,"nb_actions":6,"max_actions":1,"sum_visit_length":0,"bounce_count":6,"nb_visits_converted":0,"sum_daily_nb_uniq_visitors":6,"sum_daily_nb_users":0,"segment":"regionCode==ENG;countryCode==gb","region":"ENG","country":"gb","country_name":"United Kingdom","region_name":"England","logo":"plugins\/Morpheus\/icons\/dist\/flags\/gb.png"},{"label":"Roraima, Brazil","nb_visits":6,"nb_actions":32,"max_actions":20,"sum_visit_length":2462,"bounce_count":1,"nb_visits_converted":0,"sum_daily_nb_uniq_visitors":5,"sum_daily_nb_users":0,"segment":"regionCode==RR;countryCode==br","region":"RR","country":"br","country_name":"Brazil","region_name":"Roraima","logo":"plugins\/Morpheus\/icons\/dist\/flags\/br.png"},{"label":"Virginia, United States","nb_visits":6,"nb_actions":7,"max_actions":2,"sum_visit_length":167,"bounce_count":5,"nb_visits_converted":0,"sum_daily_nb_uniq_visitors":6,"sum_daily_nb_users":0,"segment":"regionCode==VA;countryCode==us","region":"VA","country":"us","country_name":"United States","region_name":"Virginia","logo":"plugins\/Morpheus\/icons\/dist\/flags\/us.png"},{"label":"Buenos Aires, Argentina","nb_visits":5,"nb_actions":5,"max_actions":1,"sum_visit_length":0,"bounce_count":5,"nb_visits_converted":0,"sum_daily_nb_uniq_visitors":5,"sum_daily_nb_users":0,"segment":"regionCode==B;countryCode==ar","region":"B","country":"ar","country_name":"Argentina","region_name":"Buenos Aires","logo":"plugins\/Morpheus\/icons\/dist\/flags\/ar.png"},{"label":"California, United States","nb_visits":5,"nb_actions":8,"max_actions":3,"sum_visit_length":66,"bounce_count":3,"nb_visits_converted":0,"sum_daily_nb_uniq_visitors":5,"sum_daily_nb_users":0,"segment":"regionCode==CA;countryCode==us","region":"CA","country":"us","country_name":"United States","region_name":"California","logo":"plugins\/Morpheus\/icons\/dist\/flags\/us.png"},{"label":"Texas, United States","nb_visits":4,"nb_actions":4,"max_actions":1,"sum_visit_length":0,"bounce_count":4,"nb_visits_converted":0,"sum_daily_nb_uniq_visitors":4,"sum_daily_nb_users":0,"segment":"regionCode==TX;countryCode==us","region":"TX","country":"us","country_name":"United States","region_name":"Texas","logo":"plugins\/Morpheus\/icons\/dist\/flags\/us.png"},{"label":"Braga, Portugal","nb_visits":3,"nb_actions":45,"max_actions":35,"sum_visit_length":1998,"bounce_count":0,"nb_visits_converted":0,"sum_daily_nb_uniq_visitors":2,"sum_daily_nb_users":0,"segment":"regionCode==03;countryCode==pt","region":"03","country":"pt","country_name":"Portugal","region_name":"Braga","logo":"plugins\/Morpheus\/icons\/dist\/flags\/pt.png"},{"label":"Manitoba, Canada","nb_visits":3,"nb_actions":18,"max_actions":13,"sum_visit_length":1435,"bounce_count":1,"nb_visits_converted":0,"sum_daily_nb_uniq_visitors":1,"sum_daily_nb_users":0,"segment":"regionCode==MB;countryCode==ca","region":"MB","country":"ca","country_name":"Canada","region_name":"Manitoba","logo":"plugins\/Morpheus\/icons\/dist\/flags\/ca.png"},{"label":"Florida, United States","nb_visits":2,"nb_actions":20,"max_actions":19,"sum_visit_length":3423,"bounce_count":1,"nb_visits_converted":0,"sum_daily_nb_uniq_visitors":2,"sum_daily_nb_users":0,"segment":"regionCode==FL;countryCode==us","region":"FL","country":"us","country_name":"United States","region_name":"Florida","logo":"plugins\/Morpheus\/icons\/dist\/flags\/us.png"},{"label":"Luanda, Angola","nb_visits":2,"nb_actions":2,"max_actions":1,"sum_visit_length":0,"bounce_count":2,"nb_visits_converted":0,"sum_daily_nb_uniq_visitors":2,"sum_daily_nb_users":0,"segment":"regionCode==LUA;countryCode==ao","region":"LUA","country":"ao","country_name":"Angola","region_name":"Luanda","logo":"plugins\/Morpheus\/icons\/dist\/flags\/ao.png"},{"label":"\u00cele-de-France, France","nb_visits":2,"nb_actions":8,"max_actions":7,"sum_visit_length":692,"bounce_count":1,"nb_visits_converted":0,"sum_daily_nb_uniq_visitors":2,"sum_daily_nb_users":0,"segment":"regionCode==IDF;countryCode==fr","region":"IDF","country":"fr","country_name":"France","region_name":"\u00cele-de-France","logo":"plugins\/Morpheus\/icons\/dist\/flags\/fr.png"},{"label":"Central, Paraguay","nb_visits":1,"nb_actions":1,"max_actions":1,"sum_visit_length":0,"bounce_count":1,"nb_visits_converted":0,"sum_daily_nb_uniq_visitors":1,"sum_daily_nb_users":0,"segment":"regionCode==11;countryCode==py","region":"11","country":"py","country_name":"Paraguay","region_name":"Central","logo":"plugins\/Morpheus\/icons\/dist\/flags\/py.png"},{"label":"Gaziantep, T\u00fcrkiye","nb_visits":1,"nb_actions":3,"max_actions":3,"sum_visit_length":17,"bounce_count":0,"nb_visits_converted":0,"sum_daily_nb_uniq_visitors":1,"sum_daily_nb_users":0,"segment":"regionCode==27;countryCode==tr","region":"27","country":"tr","country_name":"T\u00fcrkiye","region_name":"Gaziantep","logo":"plugins\/Morpheus\/icons\/dist\/flags\/tr.png"},{"label":"Georgia, United States","nb_visits":1,"nb_actions":2,"max_actions":2,"sum_visit_length":13,"bounce_count":0,"nb_visits_converted":0,"sum_daily_nb_uniq_visitors":1,"sum_daily_nb_users":0,"segment":"regionCode==GA;countryCode==us","region":"GA","country":"us","country_name":"United States","region_name":"Georgia","logo":"plugins\/Morpheus\/icons\/dist\/flags\/us.png"},{"label":"Madrid, Spain","nb_visits":1,"nb_actions":1,"max_actions":1,"sum_visit_length":0,"bounce_count":1,"nb_visits_converted":0,"sum_daily_nb_uniq_visitors":1,"sum_daily_nb_users":0,"segment":"regionCode==M;countryCode==es","region":"M","country":"es","country_name":"Spain","region_name":"Madrid","logo":"plugins\/Morpheus\/icons\/dist\/flags\/es.png"},{"label":"Maryland, United States","nb_visits":1,"nb_actions":1,"max_actions":1,"sum_visit_length":0,"bounce_count":1,"nb_visits_converted":0,"sum_daily_nb_uniq_visitors":1,"sum_daily_nb_users":0,"segment":"regionCode==MD;countryCode==us","region":"MD","country":"us","country_name":"United States","region_name":"Maryland","logo":"plugins\/Morpheus\/icons\/dist\/flags\/us.png"},{"label":"Montevideo, Uruguay","nb_visits":1,"nb_actions":1,"max_actions":1,"sum_visit_length":0,"bounce_count":1,"nb_visits_converted":0,"sum_daily_nb_uniq_visitors":1,"sum_daily_nb_users":0,"segment":"regionCode==MO;countryCode==uy","region":"MO","country":"uy","country_name":"Uruguay","region_name":"Montevideo","logo":"plugins\/Morpheus\/icons\/dist\/flags\/uy.png"},{"label":"New York, United States","nb_visits":1,"nb_actions":2,"max_actions":2,"sum_visit_length":15,"bounce_count":0,"nb_visits_converted":0,"sum_daily_nb_uniq_visitors":1,"sum_daily_nb_users":0,"segment":"regionCode==NY;countryCode==us","region":"NY","country":"us","country_name":"United States","region_name":"New York","logo":"plugins\/Morpheus\/icons\/dist\/flags\/us.png"},{"label":"Oklahoma, United States","nb_visits":1,"nb_actions":1,"max_actions":1,"sum_visit_length":0,"bounce_count":1,"nb_visits_converted":0,"sum_daily_nb_uniq_visitors":1,"sum_daily_nb_users":0,"segment":"regionCode==OK;countryCode==us","region":"OK","country":"us","country_name":"United States","region_name":"Oklahoma","logo":"plugins\/Morpheus\/icons\/dist\/flags\/us.png"},{"label":"Oregon, United States","nb_visits":1,"nb_actions":2,"max_actions":2,"sum_visit_length":13,"bounce_count":0,"nb_visits_converted":0,"sum_daily_nb_uniq_visitors":1,"sum_daily_nb_users":0,"segment":"regionCode==OR;countryCode==us","region":"OR","country":"us","country_name":"United States","region_name":"Oregon","logo":"plugins\/Morpheus\/icons\/dist\/flags\/us.png"},{"label":"Porto, Portugal","nb_visits":1,"nb_actions":42,"max_actions":42,"sum_visit_length":2056,"bounce_count":0,"nb_visits_converted":0,"sum_daily_nb_uniq_visitors":1,"sum_daily_nb_users":0,"segment":"regionCode==13;countryCode==pt","region":"13","country":"pt","country_name":"Portugal","region_name":"Porto","logo":"plugins\/Morpheus\/icons\/dist\/flags\/pt.png"},{"label":"Washington, United States","nb_visits":1,"nb_actions":1,"max_actions":1,"sum_visit_length":0,"bounce_count":1,"nb_visits_converted":0,"sum_daily_nb_uniq_visitors":1,"sum_daily_nb_users":0,"segment":"regionCode==WA;countryCode==us","region":"WA","country":"us","country_name":"United States","region_name":"Washington","logo":"plugins\/Morpheus\/icons\/dist\/flags\/us.png"},{"label":"West Virginia, United States","nb_visits":1,"nb_actions":1,"max_actions":1,"sum_visit_length":0,"bounce_count":1,"nb_visits_converted":0,"sum_daily_nb_uniq_visitors":1,"sum_daily_nb_users":0,"segment":"regionCode==WV;countryCode==us","region":"WV","country":"us","country_name":"United States","region_name":"West Virginia","logo":"plugins\/Morpheus\/icons\/dist\/flags\/us.png"}]